README.md
setup.py
segm8/__init__.py
segm8/font.py
segm8/output_format.py
segm8/segm8.py
segm8/segm8_exceptions.py
segm8.egg-info/PKG-INFO
segm8.egg-info/SOURCES.txt
segm8.egg-info/dependency_links.txt
segm8.egg-info/requires.txt
segm8.egg-info/top_level.txt