Metadata-Version: 2.1
Name: segm8
Version: 1.0.0
Summary: Raspberry Pi library for interaction with a chain of a particular SegM8 7-segment indicator modules.
Home-page: https://github.com/amperka/SegM8Pi/
Author: Amperka LLC
Author-email: dev@amperka.com
License: GPLv3
Platform: UNKNOWN
Classifier: Programming Language :: Python :: 3
Classifier: Programming Language :: Python :: 3.7
